{
	"cell_data": [
		"コマ■マ■ジユリツ",
		"■レイトウ■シユキ",
		"カ■ナ■リカ■ウソ",
		"ヨナオシ■ノミホ■",
		"■イ■キヨウカ■デ",
		"タカネ■ミセイネン",
		"タ■ルイ■イケガキ",
		"カカ■タカ■ツウロ"
	],
	"column_count": 9,
	"creator_info": "クロスワード ギバー ver.4.2",
	"has_hints": true,
	"has_mark": false,
	"header": "",
	"hints": {
		"h": [
			[
				1,
				"コマ",
				"駒"
			],
			[
				4,
				"ジユリツ",
				"樹立"
			],
			[
				8,
				"レイトウ",
				"冷凍"
			],
			[
				11,
				"シユキ",
				"手記"
			],
			[
				13,
				"リカ",
				"理科"
			],
			[
				15,
				"ウソ",
				"嘘"
			],
			[
				16,
				"ヨナオシ",
				"世直し"
			],
			[
				19,
				"ノミホ",
				"飲み干(す)"
			],
			[
				21,
				"キヨウカ",
				"強化"
			],
			[
				24,
				"タカネ",
				"高値"
			],
			[
				26,
				"ミセイネン",
				"未青年"
			],
			[
				28,
				"ルイ",
				"類"
			],
			[
				30,
				"イケガキ",
				"生け垣"
			],
			[
				31,
				"カカ",
				"係(わる)"
			],
			[
				32,
				"タカ",
				"高"
			],
			[
				33,
				"ツウロ",
				"通路"
			]
		],
		"v": [
			[
				2,
				"マレ",
				"稀"
			],
			[
				3,
				"マト",
				"的"
			],
			[
				5,
				"ユシ",
				"油脂"
			],
			[
				6,
				"リユウホ",
				"留保"
			],
			[
				7,
				"ツキソ",
				"付き添(う)"
			],
			[
				9,
				"イナオ",
				"居直(る)"
			],
			[
				10,
				"ウリ",
				"売り"
			],
			[
				12,
				"カヨ",
				"通(う)"
			],
			[
				14,
				"カノウセイ",
				"可能性"
			],
			[
				17,
				"ナイカ",
				"内科"
			],
			[
				18,
				"シキ",
				"四季"
			],
			[
				20,
				"ミカイケツ",
				"未解決"
			],
			[
				22,
				"ヨミ",
				"読み"
			],
			[
				23,
				"デンキロ",
				"電気炉"
			],
			[
				24,
				"タタカ",
				"闘(う)"
			],
			[
				25,
				"ネル",
				"練る"
			],
			[
				27,
				"ネガウ",
				"願う"
			],
			[
				29,
				"イタ",
				"痛(む)"
			]
		]
	},
	"is_solved": true,
	"notes": "",
	"row_count": 8
}
