{
	"cell_data": [
		"コクガイ■ニギリシ",
		"■ダツソウ■ジユン",
		"ツ■キ■ゴウ■ウシ",
		"ジユヨウ■ラクセキ",
		"ド■クマデ■ライ■",
		"ウハ■インセイ■ア",
		"■タツ■シメツケル",
		"イチヤク■コクサク"
	],
	"column_count": 9,
	"creator_info": "クロスワード ギバー ver.4.2",
	"has_hints": true,
	"has_mark": false,
	"header": "",
	"hints": {
		"h": [
			[
				1,
				"コクガイ",
				"国外"
			],
			[
				5,
				"ニギリシ",
				"握り締(める)"
			],
			[
				9,
				"ダツソウ",
				"脱走"
			],
			[
				11,
				"ジユン",
				"準"
			],
			[
				13,
				"ゴウ",
				"壕"
			],
			[
				15,
				"ウシ",
				"牛"
			],
			[
				16,
				"ジユヨウ",
				"受容"
			],
			[
				18,
				"ラクセキ",
				"落石"
			],
			[
				20,
				"クマデ",
				"熊手"
			],
			[
				22,
				"ライ",
				"来"
			],
			[
				23,
				"ウハ",
				"右派"
			],
			[
				25,
				"インセイ",
				"陰性"
			],
			[
				28,
				"タツ",
				"経つ"
			],
			[
				30,
				"シメツケル",
				"締めつける"
			],
			[
				32,
				"イチヤク",
				"一役"
			],
			[
				33,
				"コクサク",
				"国策"
			]
		],
		"v": [
			[
				2,
				"クダ",
				"管"
			],
			[
				3,
				"ガツキヨク",
				"楽曲"
			],
			[
				4,
				"イソ",
				"磯"
			],
			[
				6,
				"ギジ",
				"疑似"
			],
			[
				7,
				"リユウセイ",
				"流星"
			],
			[
				8,
				"シンシキ",
				"新式"
			],
			[
				10,
				"ウゴ",
				"動(かす)"
			],
			[
				12,
				"ツジドウ",
				"辻堂"
			],
			[
				14,
				"ウラ",
				"恨(む)"
			],
			[
				17,
				"ウマイ",
				"旨い"
			],
			[
				19,
				"クライツク",
				"食らい付く"
			],
			[
				21,
				"デンシ",
				"電子"
			],
			[
				24,
				"ハタチ",
				"二十"
			],
			[
				26,
				"セメコ",
				"攻め込(む)"
			],
			[
				27,
				"アルク",
				"歩く"
			],
			[
				29,
				"ツヤ",
				"通夜"
			],
			[
				31,
				"ケサ",
				"今朝"
			]
		]
	},
	"is_solved": true,
	"notes": "",
	"row_count": 8
}
