{
	"cell_data": [
		"カギ■シカル■カ",
		"ガ■フカイ■ダス",
		"イクツ■ワカイ■",
		"シヤカイ■ハジメ",
		"ヤク■タブン■イ",
		"■シダイ■シカシ",
		"ツヨイ■キンジヨ"
	],
	"column_count": 8,
	"creator_info": "クロスワード ギバー ver.4.2",
	"has_hints": true,
	"has_mark": false,
	"header": "",
	"hints": {
		"h": [
			[
				1,
				"カギ",
				"鍵"
			],
			[
				2,
				"シカル",
				"叱る"
			],
			[
				5,
				"フカイ",
				"深い"
			],
			[
				6,
				"ダス",
				"出す"
			],
			[
				7,
				"イクツ",
				"幾つ"
			],
			[
				9,
				"ワカイ",
				"若い"
			],
			[
				11,
				"シヤカイ",
				"社会"
			],
			[
				13,
				"ハジメ",
				"初め"
			],
			[
				15,
				"ヤク",
				"焼く"
			],
			[
				16,
				"タブン",
				"多分"
			],
			[
				17,
				"シダイ",
				"次第"
			],
			[
				19,
				"シカシ",
				"併し"
			],
			[
				21,
				"ツヨイ",
				"強い"
			],
			[
				22,
				"キンジヨ",
				"近所"
			]
		],
		"v": [
			[
				1,
				"カガイシヤ",
				"加害者"
			],
			[
				2,
				"シカ",
				"叱(る)"
			],
			[
				3,
				"カイワ",
				"会話"
			],
			[
				4,
				"カス",
				"貸す"
			],
			[
				5,
				"フツカ",
				"二日"
			],
			[
				6,
				"ダイジ",
				"大事"
			],
			[
				8,
				"クヤクシヨ",
				"区役所"
			],
			[
				10,
				"カハンシン",
				"下半身"
			],
			[
				12,
				"イタイ",
				"痛い"
			],
			[
				14,
				"メイシヨ",
				"名所"
			],
			[
				18,
				"ダイ",
				"題"
			],
			[
				20,
				"カジ",
				"火事"
			]
		]
	},
	"is_solved": true,
	"notes": "",
	"row_count": 7
}
