{"number": 68, "id": "0-0068", "level": 0, "words": [{"across": true, "clue_number": 1, "row": 0, "col": 0, "kanji_form": "七つ", "reading": "ナナツ"}, {"across": true, "clue_number": 3, "row": 0, "col": 4, "kanji_form": "五日", "reading": "イツカ"}, {"across": true, "clue_number": 5, "row": 1, "col": 3, "kanji_form": "困(る)", "reading": "コマ"}, {"across": true, "clue_number": 6, "row": 2, "col": 0, "kanji_form": "買い物", "reading": "カイモノ"}, {"across": true, "clue_number": 8, "row": 2, "col": 5, "kanji_form": "歩(く)", "reading": "アル"}, {"across": true, "clue_number": 9, "row": 3, "col": 4, "kanji_form": "並(べる)", "reading": "ナラ"}, {"across": true, "clue_number": 10, "row": 4, "col": 1, "kanji_form": "果物", "reading": "クダモノ"}, {"across": true, "clue_number": 12, "row": 5, "col": 0, "kanji_form": "熱い", "reading": "アツイ"}, {"across": true, "clue_number": 13, "row": 5, "col": 4, "kanji_form": "返す", "reading": "カエス"}, {"across": false, "clue_number": 2, "row": 0, "col": 1, "kanji_form": "長い", "reading": "ナガイ"}, {"across": false, "clue_number": 3, "row": 0, "col": 4, "kanji_form": "今", "reading": "イマ"}, {"across": false, "clue_number": 4, "row": 0, "col": 6, "kanji_form": "掛ける", "reading": "カケル"}, {"across": false, "clue_number": 5, "row": 1, "col": 3, "kanji_form": "此の", "reading": "コノ"}, {"across": false, "clue_number": 6, "row": 2, "col": 0, "kanji_form": "傘", "reading": "カサ"}, {"across": false, "clue_number": 7, "row": 2, "col": 2, "kanji_form": "問題", "reading": "モンダイ"}, {"across": false, "clue_number": 8, "row": 2, "col": 5, "kanji_form": "洗(う)", "reading": "アラ"}, {"across": false, "clue_number": 9, "row": 3, "col": 4, "kanji_form": "七日", "reading": "ナノカ"}, {"across": false, "clue_number": 10, "row": 4, "col": 1, "kanji_form": "靴", "reading": "クツ"}, {"across": false, "clue_number": 11, "row": 4, "col": 6, "kanji_form": "出す", "reading": "ダス"}]}