{"number": 32, "id": "2-0032", "level": 2, "words": [{"across": true, "clue_number": 2, "row": 0, "col": 2, "kanji_form": "引っ越(す)", "reading": "ヒツコ"}, {"across": true, "clue_number": 5, "row": 0, "col": 6, "kanji_form": "生死", "reading": "セイシ"}, {"across": true, "clue_number": 7, "row": 1, "col": 0, "kanji_form": "虫", "reading": "ムシ"}, {"across": true, "clue_number": 9, "row": 1, "col": 3, "kanji_form": "経験", "reading": "ケイケン"}, {"across": true, "clue_number": 11, "row": 2, "col": 1, "kanji_form": "掛かる", "reading": "カカル"}, {"across": true, "clue_number": 13, "row": 2, "col": 5, "kanji_form": "次第に", "reading": "シダイニ"}, {"across": true, "clue_number": 14, "row": 3, "col": 0, "kanji_form": "幾つ", "reading": "イクツ"}, {"across": true, "clue_number": 15, "row": 3, "col": 4, "kanji_form": "引き継(ぐ)", "reading": "ヒキツ"}, {"across": true, "clue_number": 16, "row": 4, "col": 0, "kanji_form": "地位", "reading": "チイ"}, {"across": true, "clue_number": 17, "row": 4, "col": 3, "kanji_form": "時機", "reading": "ジキ"}, {"across": true, "clue_number": 18, "row": 4, "col": 6, "kanji_form": "手間", "reading": "テマ"}, {"across": true, "clue_number": 20, "row": 5, "col": 2, "kanji_form": "休暇", "reading": "キユウカ"}, {"across": true, "clue_number": 22, "row": 5, "col": 7, "kanji_form": "貸し", "reading": "カシ"}, {"across": true, "clue_number": 24, "row": 6, "col": 0, "kanji_form": "遺言", "reading": "ユイゴン"}, {"across": true, "clue_number": 26, "row": 6, "col": 5, "kanji_form": "知らせる", "reading": "シラセル"}, {"across": true, "clue_number": 27, "row": 7, "col": 0, "kanji_form": "雨期", "reading": "ウキ"}, {"across": true, "clue_number": 28, "row": 7, "col": 3, "kanji_form": "美女", "reading": "ビジヨ"}, {"across": true, "clue_number": 29, "row": 7, "col": 7, "kanji_form": "留守", "reading": "ルス"}, {"across": false, "clue_number": 1, "row": 0, "col": 0, "kanji_form": "込む", "reading": "コム"}, {"across": false, "clue_number": 3, "row": 0, "col": 3, "kanji_form": "漬ける", "reading": "ツケル"}, {"across": false, "clue_number": 4, "row": 0, "col": 4, "kanji_form": "濃い", "reading": "コイ"}, {"across": false, "clue_number": 5, "row": 0, "col": 6, "kanji_form": "先だって", "reading": "センダツテ"}, {"across": false, "clue_number": 6, "row": 0, "col": 8, "kanji_form": "親日", "reading": "シンニチ"}, {"across": false, "clue_number": 8, "row": 1, "col": 1, "kanji_form": "四角い", "reading": "シカクイ"}, {"across": false, "clue_number": 10, "row": 1, "col": 5, "kanji_form": "景色", "reading": "ケシキ"}, {"across": false, "clue_number": 12, "row": 2, "col": 2, "kanji_form": "勝つ", "reading": "カツ"}, {"across": false, "clue_number": 14, "row": 3, "col": 0, "kanji_form": "一流", "reading": "イチリユウ"}, {"across": false, "clue_number": 15, "row": 3, "col": 4, "kanji_form": "引き受(ける)", "reading": "ヒキウ"}, {"across": false, "clue_number": 17, "row": 4, "col": 3, "kanji_form": "準備", "reading": "ジユンビ"}, {"across": false, "clue_number": 19, "row": 4, "col": 7, "kanji_form": "任せる", "reading": "マカセル"}, {"across": false, "clue_number": 20, "row": 5, "col": 2, "kanji_form": "季語", "reading": "キゴ"}, {"across": false, "clue_number": 21, "row": 5, "col": 5, "kanji_form": "個所", "reading": "カシヨ"}, {"across": false, "clue_number": 23, "row": 5, "col": 8, "kanji_form": "記す", "reading": "シルス"}, {"across": false, "clue_number": 25, "row": 6, "col": 1, "kanji_form": "行き", "reading": "イキ"}]}