{"number": 86, "id": "4-0086", "level": 4, "words": [{"across": true, "clue_number": 1, "row": 0, "col": 0, "kanji_form": "分かち", "reading": "ワカチ"}, {"across": true, "clue_number": 3, "row": 0, "col": 4, "kanji_form": "退場", "reading": "タイジヨウ"}, {"across": true, "clue_number": 7, "row": 1, "col": 0, "kanji_form": "力(む)", "reading": "リキ"}, {"across": true, "clue_number": 8, "row": 1, "col": 3, "kanji_form": "父", "reading": "チチ"}, {"across": true, "clue_number": 9, "row": 1, "col": 6, "kanji_form": "雑誌", "reading": "ザツシ"}, {"across": true, "clue_number": 10, "row": 2, "col": 2, "kanji_form": "学", "reading": "ガク"}, {"across": true, "clue_number": 11, "row": 2, "col": 5, "kanji_form": "零下", "reading": "レイカ"}, {"across": true, "clue_number": 12, "row": 3, "col": 0, "kanji_form": "気に入(る)", "reading": "キニイ"}, {"across": true, "clue_number": 14, "row": 3, "col": 4, "kanji_form": "版", "reading": "ハン"}, {"across": true, "clue_number": 15, "row": 3, "col": 7, "kanji_form": "何処", "reading": "ドコ"}, {"across": true, "clue_number": 17, "row": 4, "col": 3, "kanji_form": "酔っ払(う)", "reading": "ヨツパラ"}, {"across": true, "clue_number": 19, "row": 5, "col": 0, "kanji_form": "番組", "reading": "バングミ"}, {"across": true, "clue_number": 21, "row": 5, "col": 5, "kanji_form": "突っ込む", "reading": "ツツコム"}, {"across": true, "clue_number": 23, "row": 6, "col": 2, "kanji_form": "近寄(る)", "reading": "チカヨ"}, {"across": true, "clue_number": 25, "row": 6, "col": 6, "kanji_form": "堅い", "reading": "カタイ"}, {"across": true, "clue_number": 26, "row": 7, "col": 0, "kanji_form": "雨期", "reading": "ウキ"}, {"across": true, "clue_number": 27, "row": 7, "col": 3, "kanji_form": "助け", "reading": "タスケ"}, {"across": true, "clue_number": 28, "row": 7, "col": 7, "kanji_form": "演(じる)", "reading": "エン"}, {"across": false, "clue_number": 1, "row": 0, "col": 0, "kanji_form": "割り引き", "reading": "ワリビキ"}, {"across": false, "clue_number": 2, "row": 0, "col": 1, "kanji_form": "夏期", "reading": "カキ"}, {"across": false, "clue_number": 3, "row": 0, "col": 4, "kanji_form": "立ち", "reading": "タチ"}, {"across": false, "clue_number": 4, "row": 0, "col": 6, "kanji_form": "自在", "reading": "ジザイ"}, {"across": false, "clue_number": 5, "row": 0, "col": 7, "kanji_form": "四つ角", "reading": "ヨツカド"}, {"across": false, "clue_number": 6, "row": 0, "col": 8, "kanji_form": "牛", "reading": "ウシ"}, {"across": false, "clue_number": 8, "row": 1, "col": 3, "kanji_form": "地区", "reading": "チク"}, {"across": false, "clue_number": 10, "row": 2, "col": 2, "kanji_form": "害", "reading": "ガイ"}, {"across": false, "clue_number": 11, "row": 2, "col": 5, "kanji_form": "連発", "reading": "レンパツ"}, {"across": false, "clue_number": 13, "row": 3, "col": 1, "kanji_form": "二分", "reading": "ニブン"}, {"across": false, "clue_number": 14, "row": 3, "col": 4, "kanji_form": "発", "reading": "ハツ"}, {"across": false, "clue_number": 16, "row": 3, "col": 8, "kanji_form": "公務員", "reading": "コウムイン"}, {"across": false, "clue_number": 17, "row": 4, "col": 3, "kanji_form": "読み方", "reading": "ヨミカタ"}, {"across": false, "clue_number": 18, "row": 4, "col": 6, "kanji_form": "落下", "reading": "ラツカ"}, {"across": false, "clue_number": 19, "row": 5, "col": 0, "kanji_form": "梅雨", "reading": "バイウ"}, {"across": false, "clue_number": 20, "row": 5, "col": 2, "kanji_form": "愚痴", "reading": "グチ"}, {"across": false, "clue_number": 22, "row": 5, "col": 7, "kanji_form": "答", "reading": "コタエ"}, {"across": false, "clue_number": 24, "row": 6, "col": 4, "kanji_form": "止す", "reading": "ヨス"}]}