{
	"cell_data": [
		"ニ■ロウサク■カカ",
		"オウジル■シゲ■ヨ",
		"ウ■ヨ■ゲンシヨウ",
		"■ボウエイ■ユ■ビ",
		"セン■ホ■カクチ■",
		"ン■オンセイ■ヤム",
		"タイヒ■カタリクチ",
		"ク■ルイスイ■チヤ"
	],
	"column_count": 9,
	"creator_info": "クロスワード ギバー ver.4.2",
	"has_hints": true,
	"has_mark": false,
	"header": "",
	"hints": {
		"h": [
			[
				2,
				"ロウサク",
				"労作"
			],
			[
				5,
				"カカ",
				"係(わる)"
			],
			[
				7,
				"オウジル",
				"応じる"
			],
			[
				8,
				"シゲ",
				"茂(る)"
			],
			[
				10,
				"ゲンシヨウ",
				"現象"
			],
			[
				11,
				"ボウエイ",
				"防衛"
			],
			[
				13,
				"セン",
				"線"
			],
			[
				14,
				"カクチ",
				"各地"
			],
			[
				16,
				"オンセイ",
				"音声"
			],
			[
				18,
				"ヤム",
				"病む"
			],
			[
				20,
				"タイヒ",
				"対比"
			],
			[
				21,
				"カタリクチ",
				"語り口"
			],
			[
				22,
				"ルイスイ",
				"類推"
			],
			[
				23,
				"チヤ",
				"茶"
			]
		],
		"v": [
			[
				1,
				"ニオウ",
				"臭う"
			],
			[
				2,
				"ロジヨウ",
				"路上"
			],
			[
				3,
				"ウル",
				"得る"
			],
			[
				4,
				"クシン",
				"苦心"
			],
			[
				6,
				"カヨウビ",
				"火曜日"
			],
			[
				9,
				"ゲシユク",
				"下宿"
			],
			[
				10,
				"ゲイ",
				"芸"
			],
			[
				11,
				"ボン",
				"盆"
			],
			[
				12,
				"エホン",
				"絵本"
			],
			[
				13,
				"センタク",
				"選択"
			],
			[
				14,
				"カイタイ",
				"解体"
			],
			[
				15,
				"チヤクチ",
				"着地"
			],
			[
				16,
				"オヒル",
				"お昼"
			],
			[
				17,
				"セカス",
				"急かす"
			],
			[
				19,
				"ムチヤ",
				"無茶"
			]
		]
	},
	"is_solved": true,
	"notes": "",
	"row_count": 8
}
