{
	"cell_data": [
		"ネマキ■ホル■ヨキ",
		"■タ■ソロ■シロイ",
		"ニセモノ■マゴコロ",
		"クルウ■モト■バイ",
		"タ■スウチ■カス■",
		"イキ■ルイケイ■ホ",
		"■タク■エンチヨウ",
		"タイグウ■カクスル"
	],
	"column_count": 9,
	"creator_info": "クロスワード ギバー ver.4.2",
	"has_hints": true,
	"has_mark": false,
	"header": "",
	"hints": {
		"h": [
			[
				1,
				"ネマキ",
				"寝巻き"
			],
			[
				3,
				"ホル",
				"掘る"
			],
			[
				4,
				"ヨキ",
				"良き"
			],
			[
				6,
				"ソロ",
				"揃(う)"
			],
			[
				7,
				"シロイ",
				"白い"
			],
			[
				8,
				"ニセモノ",
				"偽物"
			],
			[
				10,
				"マゴコロ",
				"真心"
			],
			[
				11,
				"クルウ",
				"狂う"
			],
			[
				12,
				"モト",
				"本"
			],
			[
				13,
				"バイ",
				"倍"
			],
			[
				14,
				"スウチ",
				"数値"
			],
			[
				16,
				"カス",
				"貸す"
			],
			[
				17,
				"イキ",
				"生き"
			],
			[
				19,
				"ルイケイ",
				"類型"
			],
			[
				22,
				"タク",
				"託(す)"
			],
			[
				24,
				"エンチヨウ",
				"園長"
			],
			[
				26,
				"タイグウ",
				"待遇"
			],
			[
				27,
				"カクスル",
				"画する"
			]
		],
		"v": [
			[
				2,
				"マタセル",
				"待たせる"
			],
			[
				3,
				"ホロ",
				"滅(びる)"
			],
			[
				4,
				"ヨロコバス",
				"喜ばす"
			],
			[
				5,
				"キイロイ",
				"黄色い"
			],
			[
				6,
				"ソノ",
				"園"
			],
			[
				7,
				"シゴ",
				"私語"
			],
			[
				8,
				"ニクタイ",
				"肉体"
			],
			[
				9,
				"モウス",
				"申す"
			],
			[
				10,
				"マト",
				"的"
			],
			[
				12,
				"モチイエ",
				"持ち家"
			],
			[
				15,
				"ウル",
				"得る"
			],
			[
				16,
				"カイチク",
				"改築"
			],
			[
				18,
				"キタイ",
				"期待"
			],
			[
				20,
				"ケンカ",
				"県下"
			],
			[
				21,
				"ホウル",
				"放る"
			],
			[
				23,
				"クグ",
				"潜(る)"
			],
			[
				25,
				"ヨス",
				"止す"
			]
		]
	},
	"is_solved": true,
	"notes": "",
	"row_count": 8
}
