{
	"cell_data": [
		"ホ■タメシ■ワフウ",
		"シヒ■ザツシ■マ■",
		"■カゼ■カンデンチ",
		"ハ■ヒトリ■ア■ル",
		"ヤリトリ■ヘイヤ■",
		"イツモ■ハイ■ルス",
		"■タ■ゼンジツ■ギ",
		"ゼイカン■ツカレル"
	],
	"column_count": 9,
	"creator_info": "クロスワード ギバー ver.4.2",
	"has_hints": true,
	"has_mark": false,
	"header": "",
	"hints": {
		"h": [
			[
				2,
				"タメシ",
				"試し"
			],
			[
				5,
				"ワフウ",
				"和風"
			],
			[
				7,
				"シヒ",
				"私費"
			],
			[
				9,
				"ザツシ",
				"雑誌"
			],
			[
				11,
				"カゼ",
				"風邪"
			],
			[
				13,
				"カンデンチ",
				"乾電池"
			],
			[
				17,
				"ヒトリ",
				"一人"
			],
			[
				19,
				"ヤリトリ",
				"やり取り"
			],
			[
				21,
				"ヘイヤ",
				"平野"
			],
			[
				23,
				"イツモ",
				"何時も"
			],
			[
				24,
				"ハイ",
				"入(る)"
			],
			[
				25,
				"ルス",
				"留守"
			],
			[
				27,
				"ゼンジツ",
				"前日"
			],
			[
				29,
				"ゼイカン",
				"税関"
			],
			[
				30,
				"ツカレル",
				"疲れる"
			]
		],
		"v": [
			[
				1,
				"ホシ",
				"星"
			],
			[
				3,
				"メザ",
				"目指(す)"
			],
			[
				4,
				"シツカリ",
				"確り"
			],
			[
				6,
				"フマン",
				"不満"
			],
			[
				8,
				"ヒカ",
				"光(る)"
			],
			[
				10,
				"シン",
				"信(じる)"
			],
			[
				12,
				"ゼヒトモ",
				"是非とも"
			],
			[
				14,
				"デアイ",
				"出合い"
			],
			[
				15,
				"チル",
				"散る"
			],
			[
				16,
				"ハヤイ",
				"早い"
			],
			[
				18,
				"トリ",
				"鳥"
			],
			[
				20,
				"リツタイ",
				"立体"
			],
			[
				21,
				"ヘイジツ",
				"平日"
			],
			[
				22,
				"ヤル",
				"遣る"
			],
			[
				24,
				"ハン",
				"版"
			],
			[
				26,
				"スギル",
				"過ぎる"
			],
			[
				27,
				"ゼン",
				"全"
			],
			[
				28,
				"ツカ",
				"疲(れる)"
			]
		]
	},
	"is_solved": true,
	"notes": "",
	"row_count": 8
}
