{
	"cell_data": [
		"コウツウ■チヨツト",
		"ノンキ■キヨウツウ",
		"マ■アイヨウ■コ■",
		"シソウ■ウシロムキ",
		"イツ■キシヨウ■ヨ",
		"■ギジユツ■リコウ",
		"キヨヨウ■シヨウカ",
		"ドウシ■ウツクシイ"
	],
	"column_count": 9,
	"creator_info": "クロスワード ギバー ver.4.2",
	"has_hints": true,
	"has_mark": false,
	"header": "",
	"hints": {
		"h": [
			[
				1,
				"コウツウ",
				"交通"
			],
			[
				4,
				"チヨツト",
				"一寸"
			],
			[
				8,
				"ノンキ",
				"暢気"
			],
			[
				9,
				"キヨウツウ",
				"共通"
			],
			[
				10,
				"アイヨウ",
				"愛用"
			],
			[
				11,
				"シソウ",
				"思想"
			],
			[
				13,
				"ウシロムキ",
				"後ろ向き"
			],
			[
				16,
				"イツ",
				"何時"
			],
			[
				17,
				"キシヨウ",
				"気性"
			],
			[
				18,
				"ギジユツ",
				"技術"
			],
			[
				20,
				"リコウ",
				"利口"
			],
			[
				22,
				"キヨヨウ",
				"許容"
			],
			[
				23,
				"シヨウカ",
				"消火"
			],
			[
				24,
				"ドウシ",
				"動詞"
			],
			[
				25,
				"ウツクシイ",
				"美しい"
			]
		],
		"v": [
			[
				1,
				"コノマシイ",
				"好ましい"
			],
			[
				2,
				"ウン",
				"運"
			],
			[
				3,
				"ツキアウ",
				"付き合う"
			],
			[
				4,
				"チヨウシヨ",
				"長所"
			],
			[
				5,
				"ヨウ",
				"酔う"
			],
			[
				6,
				"ツツコム",
				"突っ込む"
			],
			[
				7,
				"トウ",
				"党"
			],
			[
				9,
				"キヨウシツ",
				"教室"
			],
			[
				12,
				"ソツギヨウ",
				"卒業"
			],
			[
				14,
				"ロウリヨク",
				"労力"
			],
			[
				15,
				"キヨウカイ",
				"教会"
			],
			[
				17,
				"キユウ",
				"九"
			],
			[
				19,
				"ジヨシ",
				"女子"
			],
			[
				21,
				"コウシ",
				"講師"
			],
			[
				22,
				"キド",
				"気取(る)"
			],
			[
				23,
				"シツ",
				"質"
			]
		]
	},
	"is_solved": true,
	"notes": "",
	"row_count": 8
}
